pyropes/Ropes.py
pyropes/__init__.py
pyropes-1.4.dist-info/LICENSE
pyropes-1.4.dist-info/METADATA
pyropes-1.4.dist-info/WHEEL
pyropes-1.4.dist-info/top_level.txt
pyropes-1.4.dist-info/RECORD
