Metadata-Version: 2.1
Name: pyropes
Version: 1.4
Summary: An implementation of Height Balanced Threaded Rope Data Structure in Python3
Home-page: https://github.com/mradultiw/pyropes
Author: Mradul Tiwari
Author-email: complex.m15@gmail.com
License: UNKNOWN
Project-URL: Source, https://github.com/mradultiw/pyropes
Platform: UNKNOWN
Classifier: Intended Audience :: Education
Classifier: Intended Audience :: Developers
Classifier: Intended Audience :: Information Technology
Classifier: Development Status :: 5 - Production/Stable
Classifier: Programming Language :: Python :: 3
Classifier: License :: OSI Approved :: Apache Software License
Classifier: Operating System :: OS Independent
Classifier: Topic :: Education
Classifier: Topic :: Utilities
Requires-Python: >=3.6
